<?xml version="1.0" encoding="utf-8"?>
<databaseChangeLog
    xmlns="http://www.liquibase.org/xml/ns/dbchangelog"
    xmlns:ext="http://www.liquibase.org/xml/ns/dbchangelog-ext"
    xmlns:xsi="http://www.w3.org/2001/XMLSchema-instance"
    xsi:schemaLocation="http://www.liquibase.org/xml/ns/dbchangelog http://www.liquibase.org/xml/ns/dbchangelog/dbchangelog-4.6.xsd
                        http://www.liquibase.org/xml/ns/dbchangelog-ext http://www.liquibase.org/xml/ns/dbchangelog/dbchangelog-ext.xsd">

    <!--
        Added the entity Auditoria.
    -->
    <changeSet id="20221027145917-1" author="jhipster">
        <createTable tableName="auditoria">
            <column name="id" type="bigint">
                <constraints primaryKey="true" nullable="false"/>
            </column>
            <column name="usuario_creacion" type="bigint">
                <constraints nullable="true" />
            </column>
            <column name="fecha_creacion" type="${datetimeType}">
                <constraints nullable="true" />
            </column>
            <column name="usuario_modificacion" type="bigint">
                <constraints nullable="true" />
            </column>
            <column name="fecha_modificacion" type="${datetimeType}">
                <constraints nullable="true" />
            </column>
            <column name="request" type="varchar(255)">
                <constraints nullable="true" />
            </column>
            <column name="response" type="varchar(255)">
                <constraints nullable="true" />
            </column>
            <!-- jhipster-needle-liquibase-add-column - JHipster will add columns here -->
        </createTable>
        <dropDefaultValue tableName="auditoria" columnName="fecha_creacion" columnDataType="${datetimeType}"/>
        <dropDefaultValue tableName="auditoria" columnName="fecha_modificacion" columnDataType="${datetimeType}"/>
    </changeSet>

    <!-- jhipster-needle-liquibase-add-changeset - JHipster will add changesets here -->

    
</databaseChangeLog>
